{
    "asset": {
        "version": "0.0"
    },
    "geometricError": 4.0,
    "root": {
        "boundingVolume": {
            "sphere": [
                -888.697891304,
                394.990282609,
                4.26650333335,
                11.409455759021155
            ]
        },
        "refine": "replace",
        "geometricError": 2.0,
        "content": {
            "url": "tile_4_10_12_tex.b3dm"
        },
        "children": [
            {
                "boundingVolume": {
                    "sphere": [
                        -892.6041413042,
                        391.0840326087,
                        5.206044289499999,
                        5.593698836880619
                    ]
                },
                "geometricError": 1.0,
                "content": {
                    "url": "tile_5_10_12_tex.b3dm"
                }
            },
            {
                "boundingVolume": {
                    "sphere": [
                        -892.6041413042,
                        398.8965326087,
                        3.1424139205,
                        5.786706691647144
                    ]
                },
                "geometricError": 1.0,
                "content": {
                    "url": "tile_5_10_13_tex.b3dm"
                }
            },
            {
                "boundingVolume": {
                    "sphere": [
                        -884.7916413042,
                        391.0840326087,
                        5.62883448675,
                        5.732206938141971
                    ]
                },
                "geometricError": 1.0,
                "content": {
                    "url": "tile_5_11_12_tex.b3dm"
                }
            },
            {
                "boundingVolume": {
                    "sphere": [
                        -884.7916413042,
                        398.8965326087,
                        3.135422161,
                        5.76818719897767
                    ]
                },
                "geometricError": 1.0,
                "content": {
                    "url": "tile_5_11_13_tex.b3dm"
                }
            }
        ]
    }
}