{
    "asset": {
        "version": "0.0"
    },
    "geometricError": 16.0,
    "root": {
        "boundingVolume": {
            "sphere": [
                -880.8853913042,
                637.1777826087,
                5.1854190917,
                45.07776747666006
            ]
        },
        "refine": "replace",
        "geometricError": 8.0,
        "content": {
            "url": "tile_2_8_8_tex.b3dm"
        },
        "children": [
            {
                "boundingVolume": {
                    "sphere": [
                        -896.5103913042,
                        621.5527826087,
                        4.369096948299999,
                        23.166313230982206
                    ]
                },
                "geometricError": 4.0,
                "content": {
                    "url": "tile_3_8_8_tex.json"
                }
            },
            {
                "boundingVolume": {
                    "sphere": [
                        -896.5103913042,
                        652.8027826087,
                        1.53954263895,
                        22.72457618691816
                    ]
                },
                "geometricError": 4.0,
                "content": {
                    "url": "tile_3_8_12_tex.json"
                }
            },
            {
                "boundingVolume": {
                    "sphere": [
                        -865.2603913042,
                        621.5527826087,
                        7.8654963350000008,
                        22.981109092049434
                    ]
                },
                "geometricError": 4.0,
                "content": {
                    "url": "tile_3_12_8_tex.json"
                }
            },
            {
                "boundingVolume": {
                    "sphere": [
                        -865.2603913042,
                        652.8027826087,
                        5.816817045,
                        22.7620111555363
                    ]
                },
                "geometricError": 4.0,
                "content": {
                    "url": "tile_3_12_12_tex.json"
                }
            }
        ]
    }
}