{
    "asset": {
        "version": "0.0"
    },
    "geometricError": 8.0,
    "root": {
        "boundingVolume": {
            "sphere": [
                -740.2603913042,
                590.3027826087,
                6.5015964793,
                22.81841462660602
            ]
        },
        "refine": "replace",
        "geometricError": 4.0,
        "content": {
            "url": "tile_3_28_4_tex.b3dm"
        },
        "children": [
            {
                "boundingVolume": {
                    "sphere": [
                        -748.0728913042,
                        582.4902826087,
                        5.32866028995,
                        11.524647154239613
                    ]
                },
                "geometricError": 2.0,
                "content": {
                    "url": "tile_4_28_4_tex.json"
                }
            },
            {
                "boundingVolume": {
                    "sphere": [
                        -748.0728913042,
                        598.1152826087,
                        6.67640876825,
                        12.127543479584
                    ]
                },
                "geometricError": 2.0,
                "content": {
                    "url": "tile_4_28_6_tex.json"
                }
            },
            {
                "boundingVolume": {
                    "sphere": [
                        -732.4478913042,
                        582.4902826087,
                        3.0382620313000006,
                        11.285787298086227
                    ]
                },
                "geometricError": 2.0,
                "content": {
                    "url": "tile_4_30_4_tex.json"
                }
            },
            {
                "boundingVolume": {
                    "sphere": [
                        -732.4478913042,
                        598.1152826087,
                        7.04059244835,
                        12.25512240561496
                    ]
                },
                "geometricError": 2.0,
                "content": {
                    "url": "tile_4_30_6_tex.json"
                }
            }
        ]
    }
}