{
    "asset": {
        "version": "0.0"
    },
    "geometricError": 4.0,
    "root": {
        "boundingVolume": {
            "sphere": [
                -998.0728913036,
                629.365282609,
                5.6968332221499999,
                11.061615177530399
            ]
        },
        "refine": "replace",
        "geometricError": 2.0,
        "content": {
            "url": "tile_4_28_10_tex.b3dm"
        },
        "children": [
            {
                "boundingVolume": {
                    "sphere": [
                        -1001.9791413042,
                        625.4590326087,
                        5.721421509000001,
                        5.544807902093414
                    ]
                },
                "geometricError": 1.0,
                "content": {
                    "url": "tile_5_28_10_tex.b3dm"
                }
            },
            {
                "boundingVolume": {
                    "sphere": [
                        -1001.9791413042,
                        633.2715326087,
                        5.5075558995,
                        5.535242492823087
                    ]
                },
                "geometricError": 1.0,
                "content": {
                    "url": "tile_5_28_11_tex.b3dm"
                }
            },
            {
                "boundingVolume": {
                    "sphere": [
                        -994.1666413042,
                        625.4590326087,
                        5.704093293,
                        5.531945963116054
                    ]
                },
                "geometricError": 1.0,
                "content": {
                    "url": "tile_5_29_10_tex.b3dm"
                }
            },
            {
                "boundingVolume": {
                    "sphere": [
                        -994.1666413042,
                        633.2715326087,
                        5.5998018195,
                        5.531142173379294
                    ]
                },
                "geometricError": 1.0,
                "content": {
                    "url": "tile_5_29_11_tex.b3dm"
                }
            }
        ]
    }
}