{
    "asset": {
        "version": "0.0"
    },
    "geometricError": 4.0,
    "root": {
        "boundingVolume": {
            "sphere": [
                -1201.19789130035,
                598.115282609,
                26.81746603305,
                24.274705822787337
            ]
        },
        "refine": "replace",
        "geometricError": 2.0,
        "content": {
            "url": "tile_4_2_6_tex.b3dm"
        },
        "children": [
            {
                "boundingVolume": {
                    "sphere": [
                        -1205.1041413042,
                        594.2090326087,
                        6.288001595,
                        5.603989121693313
                    ]
                },
                "geometricError": 1.0,
                "content": {
                    "url": "tile_5_2_6_tex.b3dm"
                }
            },
            {
                "boundingVolume": {
                    "sphere": [
                        -1205.1041413042,
                        602.0215326087,
                        6.2309946745,
                        5.594706334722024
                    ]
                },
                "geometricError": 1.0,
                "content": {
                    "url": "tile_5_2_7_tex.b3dm"
                }
            },
            {
                "boundingVolume": {
                    "sphere": [
                        -1197.2916413042,
                        594.2090326087,
                        26.40403612385,
                        21.874563740138635
                    ]
                },
                "geometricError": 1.0,
                "content": {
                    "url": "tile_5_3_6_tex.b3dm"
                }
            },
            {
                "boundingVolume": {
                    "sphere": [
                        -1197.2916413042,
                        602.0215326087,
                        26.81441510745,
                        22.312339784962754
                    ]
                },
                "geometricError": 1.0,
                "content": {
                    "url": "tile_5_3_7_tex.b3dm"
                }
            }
        ]
    }
}