{
    "asset": {
        "version": "0.0"
    },
    "geometricError": 4.0,
    "root": {
        "boundingVolume": {
            "sphere": [
                -1201.19789130035,
                629.365282609,
                5.7465744649,
                11.188311703068184
            ]
        },
        "refine": "replace",
        "geometricError": 2.0,
        "content": {
            "url": "tile_4_2_10_tex.b3dm"
        },
        "children": [
            {
                "boundingVolume": {
                    "sphere": [
                        -1205.1041413042,
                        625.4590326087,
                        6.364689837849999,
                        5.556247169396676
                    ]
                },
                "geometricError": 1.0,
                "content": {
                    "url": "tile_5_2_10_tex.b3dm"
                }
            },
            {
                "boundingVolume": {
                    "sphere": [
                        -1205.1041413042,
                        633.2715326087,
                        5.70725100745,
                        5.786004390448405
                    ]
                },
                "geometricError": 1.0,
                "content": {
                    "url": "tile_5_2_11_tex.b3dm"
                }
            },
            {
                "boundingVolume": {
                    "sphere": [
                        -1197.2916413042,
                        625.4590326087,
                        6.560743907999999,
                        5.60515565977196
                    ]
                },
                "geometricError": 1.0,
                "content": {
                    "url": "tile_5_3_10_tex.b3dm"
                }
            },
            {
                "boundingVolume": {
                    "sphere": [
                        -1197.2916413042,
                        633.2715326087,
                        6.32316508595,
                        5.563013841665463
                    ]
                },
                "geometricError": 1.0,
                "content": {
                    "url": "tile_5_3_11_tex.b3dm"
                }
            }
        ]
    }
}