{
    "asset": {
        "version": "0.0"
    },
    "geometricError": 4.0,
    "root": {
        "boundingVolume": {
            "sphere": [
                -1419.9478913042,
                410.6152826087,
                5.0067373292,
                11.517970617672967
            ]
        },
        "refine": "replace",
        "geometricError": 2.0,
        "content": {
            "url": "tile_4_6_14_tex.b3dm"
        },
        "children": [
            {
                "boundingVolume": {
                    "sphere": [
                        -1423.8541413042,
                        406.7090326087,
                        3.42216860915,
                        5.611636543360409
                    ]
                },
                "geometricError": 1.0,
                "content": {
                    "url": "tile_5_6_14_tex.b3dm"
                }
            },
            {
                "boundingVolume": {
                    "sphere": [
                        -1423.8541413042,
                        414.5215326087,
                        4.2662190201,
                        5.98939332266932
                    ]
                },
                "geometricError": 1.0,
                "content": {
                    "url": "tile_5_6_15_tex.b3dm"
                }
            },
            {
                "boundingVolume": {
                    "sphere": [
                        -1416.0416413042,
                        406.7090326087,
                        4.1741577652,
                        6.031951668120375
                    ]
                },
                "geometricError": 1.0,
                "content": {
                    "url": "tile_5_7_14_tex.b3dm"
                }
            },
            {
                "boundingVolume": {
                    "sphere": [
                        -1416.0416413042,
                        414.5215326087,
                        5.4605086938500009,
                        6.213578677153518
                    ]
                },
                "geometricError": 1.0,
                "content": {
                    "url": "tile_5_7_15_tex.b3dm"
                }
            }
        ]
    }
}