{
    "asset": {
        "version": "0.0"
    },
    "geometricError": 8.0,
    "root": {
        "boundingVolume": {
            "sphere": [
                -1052.7603913027502,
                309.052782609,
                95.00120080465,
                93.81726997390648
            ]
        },
        "refine": "replace",
        "geometricError": 4.0,
        "content": {
            "url": "tile_3_20_0_tex.b3dm"
        },
        "children": [
            {
                "boundingVolume": {
                    "sphere": [
                        -1060.5728913026,
                        301.240282609,
                        32.5951498501,
                        30.81310434420346
                    ]
                },
                "geometricError": 2.0,
                "content": {
                    "url": "tile_4_20_0_tex.json"
                }
            },
            {
                "boundingVolume": {
                    "sphere": [
                        -1060.5728913026,
                        316.865282609,
                        58.77214906855,
                        11.335140251034755
                    ]
                },
                "geometricError": 2.0,
                "content": {
                    "url": "tile_4_20_2_tex.json"
                }
            },
            {
                "boundingVolume": {
                    "sphere": [
                        -1044.9478913028502,
                        301.240282609,
                        95.04978438065,
                        91.75927261180263
                    ]
                },
                "geometricError": 2.0,
                "content": {
                    "url": "tile_4_22_0_tex.json"
                }
            },
            {
                "boundingVolume": {
                    "sphere": [
                        -1044.9478913028502,
                        316.865282609,
                        121.05756224205001,
                        65.6325901330287
                    ]
                },
                "geometricError": 2.0,
                "content": {
                    "url": "tile_4_22_2_tex.json"
                }
            }
        ]
    }
}