{
    "asset": {
        "version": "0.0"
    },
    "geometricError": 4.0,
    "root": {
        "boundingVolume": {
            "sphere": [
                -1044.9478913028502,
                410.615282609,
                30.10496373495,
                29.35152338990284
            ]
        },
        "refine": "replace",
        "geometricError": 2.0,
        "content": {
            "url": "tile_4_22_14_tex.b3dm"
        },
        "children": [
            {
                "boundingVolume": {
                    "sphere": [
                        -1048.8541413042,
                        406.70903260865,
                        28.676833141000004,
                        25.294133758189756
                    ]
                },
                "geometricError": 1.0,
                "content": {
                    "url": "tile_5_22_14_tex.b3dm"
                }
            },
            {
                "boundingVolume": {
                    "sphere": [
                        -1048.8541413042,
                        414.5215326087,
                        30.315245122150004,
                        27.542369009638838
                    ]
                },
                "geometricError": 1.0,
                "content": {
                    "url": "tile_5_22_15_tex.b3dm"
                }
            },
            {
                "boundingVolume": {
                    "sphere": [
                        -1041.0416413042,
                        406.70903260865,
                        28.536933071,
                        25.28732984350259
                    ]
                },
                "geometricError": 1.0,
                "content": {
                    "url": "tile_5_23_14_tex.b3dm"
                }
            },
            {
                "boundingVolume": {
                    "sphere": [
                        -1041.0416413042,
                        414.5215326087,
                        27.9572235156,
                        25.640818691977477
                    ]
                },
                "geometricError": 1.0,
                "content": {
                    "url": "tile_5_23_15_tex.b3dm"
                }
            }
        ]
    }
}