{
    "asset": {
        "version": "0.0"
    },
    "geometricError": 4.0,
    "root": {
        "boundingVolume": {
            "sphere": [
                -1044.9478913028502,
                301.240282609,
                95.04978438065,
                91.75927261180263
            ]
        },
        "refine": "replace",
        "geometricError": 2.0,
        "content": {
            "url": "tile_4_22_0_tex.b3dm"
        },
        "children": [
            {
                "boundingVolume": {
                    "sphere": [
                        -1048.8541413042,
                        297.33403260885,
                        5.2531610420499998,
                        5.637904781533494
                    ]
                },
                "geometricError": 1.0,
                "content": {
                    "url": "tile_5_22_0_tex.b3dm"
                }
            },
            {
                "boundingVolume": {
                    "sphere": [
                        -1048.8541413042,
                        305.1465326087,
                        94.79248773500001,
                        91.00221102259295
                    ]
                },
                "geometricError": 1.0,
                "content": {
                    "url": "tile_5_22_1_tex.b3dm"
                }
            },
            {
                "boundingVolume": {
                    "sphere": [
                        -1041.0416413042,
                        297.33403260885,
                        7.3449384829,
                        6.430089929623631
                    ]
                },
                "geometricError": 1.0,
                "content": {
                    "url": "tile_5_23_0_tex.b3dm"
                }
            },
            {
                "boundingVolume": {
                    "sphere": [
                        -1041.0416413042,
                        305.1465326087,
                        95.13688162545,
                        91.17209712145633
                    ]
                },
                "geometricError": 1.0,
                "content": {
                    "url": "tile_5_23_1_tex.b3dm"
                }
            }
        ]
    }
}