{
    "asset": {
        "version": "0.0"
    },
    "geometricError": 4.0,
    "root": {
        "boundingVolume": {
            "sphere": [
                -1044.9478913028502,
                676.240282609,
                30.3617451746,
                26.96952974337458
            ]
        },
        "refine": "replace",
        "geometricError": 2.0,
        "content": {
            "url": "tile_4_22_16_tex.b3dm"
        },
        "children": [
            {
                "boundingVolume": {
                    "sphere": [
                        -1048.8541413042,
                        672.3340326087,
                        44.1845452615,
                        12.119926287451092
                    ]
                },
                "geometricError": 1.0,
                "content": {
                    "url": "tile_5_22_16_tex.b3dm"
                }
            },
            {
                "boundingVolume": {
                    "sphere": [
                        -1048.8541413042,
                        680.1465326087,
                        30.32502559055,
                        24.514159325804515
                    ]
                },
                "geometricError": 1.0,
                "content": {
                    "url": "tile_5_22_17_tex.b3dm"
                }
            },
            {
                "boundingVolume": {
                    "sphere": [
                        -1041.0416413042,
                        672.3340326087,
                        43.63916612965,
                        12.293263199820763
                    ]
                },
                "geometricError": 1.0,
                "content": {
                    "url": "tile_5_23_16_tex.b3dm"
                }
            },
            {
                "boundingVolume": {
                    "sphere": [
                        -1041.0416413042,
                        680.1465326087,
                        23.238924797000004,
                        18.339183767849286
                    ]
                },
                "geometricError": 1.0,
                "content": {
                    "url": "tile_5_23_17_tex.b3dm"
                }
            }
        ]
    }
}