{
    "asset": {
        "version": "0.0"
    },
    "geometricError": 4.0,
    "root": {
        "boundingVolume": {
            "sphere": [
                -998.0728913036,
                738.740282609,
                8.331973282349999,
                13.296386051269213
            ]
        },
        "refine": "replace",
        "geometricError": 2.0,
        "content": {
            "url": "tile_4_28_24_tex.b3dm"
        },
        "children": [
            {
                "boundingVolume": {
                    "sphere": [
                        -1001.9791413042,
                        734.8340326087,
                        10.20885578615,
                        7.809943407281344
                    ]
                },
                "geometricError": 1.0,
                "content": {
                    "url": "tile_5_28_24_tex.b3dm"
                }
            },
            {
                "boundingVolume": {
                    "sphere": [
                        -1001.9791413042,
                        742.6465326087,
                        6.7850099787,
                        8.0283959026901
                    ]
                },
                "geometricError": 1.0,
                "content": {
                    "url": "tile_5_28_25_tex.b3dm"
                }
            },
            {
                "boundingVolume": {
                    "sphere": [
                        -994.1666413042,
                        734.8340326087,
                        10.369391151350002,
                        6.164932399934454
                    ]
                },
                "geometricError": 1.0,
                "content": {
                    "url": "tile_5_29_24_tex.b3dm"
                }
            },
            {
                "boundingVolume": {
                    "sphere": [
                        -994.1666413042,
                        742.6465326087,
                        7.396674105,
                        7.8170815800415689
                    ]
                },
                "geometricError": 1.0,
                "content": {
                    "url": "tile_5_29_25_tex.b3dm"
                }
            }
        ]
    }
}