{
    "asset": {
        "version": "0.0"
    },
    "geometricError": 4.0,
    "root": {
        "boundingVolume": {
            "sphere": [
                -935.5728913042,
                785.6152826087,
                5.3823865741,
                11.309150401453119
            ]
        },
        "refine": "replace",
        "geometricError": 2.0,
        "content": {
            "url": "tile_4_4_30_tex.b3dm"
        },
        "children": [
            {
                "boundingVolume": {
                    "sphere": [
                        -939.4791413042,
                        781.7090326087,
                        4.7915795140499999,
                        5.817300663873031
                    ]
                },
                "geometricError": 1.0,
                "content": {
                    "url": "tile_5_4_30_tex.b3dm"
                }
            },
            {
                "boundingVolume": {
                    "sphere": [
                        -939.4791413042,
                        789.5215326087,
                        5.96844386725,
                        5.684077310191116
                    ]
                },
                "geometricError": 1.0,
                "content": {
                    "url": "tile_5_4_31_tex.b3dm"
                }
            },
            {
                "boundingVolume": {
                    "sphere": [
                        -931.6666413042,
                        781.7090326087,
                        4.10382800075,
                        5.6306691824635088
                    ]
                },
                "geometricError": 1.0,
                "content": {
                    "url": "tile_5_5_30_tex.b3dm"
                }
            },
            {
                "boundingVolume": {
                    "sphere": [
                        -931.6666413042,
                        789.5215326087,
                        5.86968318145,
                        5.850564509032165
                    ]
                },
                "geometricError": 1.0,
                "content": {
                    "url": "tile_5_5_31_tex.b3dm"
                }
            }
        ]
    }
}