{
    "asset": {
        "version": "0.0"
    },
    "geometricError": 4.0,
    "root": {
        "boundingVolume": {
            "sphere": [
                -1419.9478913042,
                519.9902826087,
                4.33221338115,
                11.72619774951396
            ]
        },
        "refine": "replace",
        "geometricError": 2.0,
        "content": {
            "url": "tile_4_6_28_tex.b3dm"
        },
        "children": [
            {
                "boundingVolume": {
                    "sphere": [
                        -1423.8541413042,
                        516.0840326087,
                        5.59272728295,
                        6.155355745983306
                    ]
                },
                "geometricError": 1.0,
                "content": {
                    "url": "tile_5_6_28_tex.b3dm"
                }
            },
            {
                "boundingVolume": {
                    "sphere": [
                        -1423.8541413042,
                        523.8965326087,
                        3.4891160635,
                        5.726540250575769
                    ]
                },
                "geometricError": 1.0,
                "content": {
                    "url": "tile_5_6_29_tex.b3dm"
                }
            },
            {
                "boundingVolume": {
                    "sphere": [
                        -1416.0416413042,
                        516.0840326087,
                        5.03623451925,
                        6.393818781997776
                    ]
                },
                "geometricError": 1.0,
                "content": {
                    "url": "tile_5_7_28_tex.b3dm"
                }
            },
            {
                "boundingVolume": {
                    "sphere": [
                        -1416.0416413042,
                        523.8965326087,
                        2.71411325315,
                        5.96585143150554
                    ]
                },
                "geometricError": 1.0,
                "content": {
                    "url": "tile_5_7_29_tex.b3dm"
                }
            }
        ]
    }
}