{
    "asset": {
        "version": "0.0"
    },
    "geometricError": 4.0,
    "root": {
        "boundingVolume": {
            "sphere": [
                -1326.1978913042,
                473.1152826087,
                3.89792197775,
                11.200457281989241
            ]
        },
        "refine": "replace",
        "geometricError": 2.0,
        "content": {
            "url": "tile_4_18_22_tex.b3dm"
        },
        "children": [
            {
                "boundingVolume": {
                    "sphere": [
                        -1330.1041413042,
                        469.2090326087,
                        4.2590134827,
                        5.720621727193309
                    ]
                },
                "geometricError": 1.0,
                "content": {
                    "url": "tile_5_18_22_tex.b3dm"
                }
            },
            {
                "boundingVolume": {
                    "sphere": [
                        -1330.1041413042,
                        477.0215326087,
                        3.4489538178499998,
                        5.693566321090986
                    ]
                },
                "geometricError": 1.0,
                "content": {
                    "url": "tile_5_18_23_tex.b3dm"
                }
            },
            {
                "boundingVolume": {
                    "sphere": [
                        -1322.2916413042,
                        469.2090326087,
                        4.4577391452,
                        5.661363568887789
                    ]
                },
                "geometricError": 1.0,
                "content": {
                    "url": "tile_5_19_22_tex.b3dm"
                }
            },
            {
                "boundingVolume": {
                    "sphere": [
                        -1322.2916413042,
                        477.0215326087,
                        4.3013600189,
                        5.607146092690041
                    ]
                },
                "geometricError": 1.0,
                "content": {
                    "url": "tile_5_19_23_tex.b3dm"
                }
            }
        ]
    }
}