{
    "asset": {
        "version": "0.0"
    },
    "geometricError": 4.0,
    "root": {
        "boundingVolume": {
            "sphere": [
                -1466.8228913042,
                582.4902826087,
                14.015857727299999,
                11.409079999351106
            ]
        },
        "refine": "replace",
        "geometricError": 2.0,
        "content": {
            "url": "tile_4_0_4_tex.b3dm"
        },
        "children": [
            {
                "boundingVolume": {
                    "sphere": [
                        -1470.7291413042,
                        578.5840326087,
                        13.91341247535,
                        5.645147022875632
                    ]
                },
                "geometricError": 1.0,
                "content": {
                    "url": "tile_5_0_4_tex.b3dm"
                }
            },
            {
                "boundingVolume": {
                    "sphere": [
                        -1470.7291413042,
                        586.3965326087,
                        15.3584665537,
                        5.7249937751408279
                    ]
                },
                "geometricError": 1.0,
                "content": {
                    "url": "tile_5_0_5_tex.b3dm"
                }
            },
            {
                "boundingVolume": {
                    "sphere": [
                        -1462.9166413042,
                        578.5840326087,
                        12.63175928525,
                        5.658257610605394
                    ]
                },
                "geometricError": 1.0,
                "content": {
                    "url": "tile_5_1_4_tex.b3dm"
                }
            },
            {
                "boundingVolume": {
                    "sphere": [
                        -1462.9166413042,
                        586.3965326087,
                        12.6557539345,
                        5.7190367643958439
                    ]
                },
                "geometricError": 1.0,
                "content": {
                    "url": "tile_5_1_5_tex.b3dm"
                }
            }
        ]
    }
}